mpl_simple_svg_parser/__init__.py
mpl_simple_svg_parser/_version.py
mpl_simple_svg_parser/cairo_numpy_surface.py
mpl_simple_svg_parser/gradient_param.py
mpl_simple_svg_parser/picosvg_helper.py
mpl_simple_svg_parser/svg_gradient_helper.py
mpl_simple_svg_parser/svg_helper.py
mpl_simple_svg_parser/svg_mpl_path_iterator.py
mpl_simple_svg_parser/svg_xml_helper.py
mpl_simple_svg_parser/tests/__init__.py
mpl_simple_svg_parser/tests/test_example.py
mpl_simple_svg_parser-0.2.1.dist-info/LICENSE
mpl_simple_svg_parser-0.2.1.dist-info/METADATA
mpl_simple_svg_parser-0.2.1.dist-info/WHEEL
mpl_simple_svg_parser-0.2.1.dist-info/top_level.txt
mpl_simple_svg_parser-0.2.1.dist-info/RECORD
